decimal_monkeypatch/__init__.py
decimal_monkeypatch/bootstrap.py
decimal_monkeypatch/patch.py
decimal_monkeypatch/__startup__/sitecustomize.py
decimal_monkeypatch-0.4.3.data/data/lib/python2.7/dist-packages/autowrapt-init.pth
decimal_monkeypatch-0.4.3.dist-info/DESCRIPTION.rst
decimal_monkeypatch-0.4.3.dist-info/METADATA
decimal_monkeypatch-0.4.3.dist-info/RECORD
decimal_monkeypatch-0.4.3.dist-info/WHEEL
decimal_monkeypatch-0.4.3.dist-info/entry_points.txt
decimal_monkeypatch-0.4.3.dist-info/metadata.json
decimal_monkeypatch-0.4.3.dist-info/top_level.txt
