Metadata-Version: 2.0
Name: decimal-monkeypatch
Version: 0.4.3
Summary: Python 2 performance patches: decimal to cdecimal, json to ujson for psycopg2
Home-page: https://github.com/IaroslavR/decimal-monkeypatch
Author: Iaroslav Russkykh
Author-email: iarrus@ya.ru
License: BSD
Platform: UNKNOWN
Requires-Dist: m3-cdecimal (==2.3)
Requires-Dist: ujson (==1.35)
Requires-Dist: wrapt (>=1.10.4)
